dbanu/__init__.py
dbanu/api/__init__.py
dbanu/api/dependencies.py
dbanu/api/select.py
dbanu/api/union.py
dbanu/core/__init__.py
dbanu/core/engine.py
dbanu/core/middleware.py
dbanu/core/response.py
dbanu/engines/__init__.py
dbanu/engines/mysql.py
dbanu/engines/postgresql.py
dbanu/engines/sqlite.py
dbanu/utils/__init__.py
dbanu/utils/filter.py
dbanu/utils/pagination.py
dbanu/utils/param.py
dbanu/utils/string.py
dbanu-0.1.0.dist-info/METADATA
dbanu-0.1.0.dist-info/WHEEL
dbanu-0.1.0.dist-info/RECORD
