Metadata-Version: 2.4
Name: dbanu
Version: 0.1.0
Summary: FastAPI SQL Query Engine
License: MIT
Author: gofrendi
Author-email: gofrendiasgard@gmail.com
Requires-Python: >=3.11
Classifier: License :: OSI Approved :: MIT License
Classifier: Programming Language :: Python :: 3
Classifier: Programming Language :: Python :: 3.11
Classifier: Programming Language :: Python :: 3.12
Classifier: Programming Language :: Python :: 3.13
Classifier: Programming Language :: Python :: 3.14
Requires-Dist: fastapi (>=0.118.3)
Requires-Dist: mysql-connector-python (>=9.4.0,<10.0.0)
Requires-Dist: psycopg2-binary (>=2.9.11,<3.0.0)
Requires-Dist: uvicorn (>=0.38.0)
